speedystats/__init__.py
speedystats/routing.py
speedystats/speedystats.py
speedystats/numba/__init__.py
speedystats/numba/average.py
speedystats/numba/mean.py
speedystats/numba/median.py
speedystats/numba/nanmean.py
speedystats/numba/nanmedian.py
speedystats/numba/nanpercentile.py
speedystats/numba/nanquantile.py
speedystats/numba/nanstd.py
speedystats/numba/nansum.py
speedystats/numba/nanvar.py
speedystats/numba/percentile.py
speedystats/numba/ptp.py
speedystats/numba/quantile.py
speedystats/numba/std.py
speedystats/numba/sum.py
speedystats/numba/var.py
speedystats-0.0.1.dist-info/METADATA
speedystats-0.0.1.dist-info/WHEEL
speedystats-0.0.1.dist-info/licenses/LICENSE
speedystats-0.0.1.dist-info/RECORD
