Metadata-Version: 2.4
Name: speedystats
Version: 0.0.1
Summary: A simple package to support fast statistics.
Project-URL: Homepage, https://github.com/landoskape/speedystats
Author-email: Andrew Landau <andrew+tyler+landau+getridofthisanddtheplusses@gmail.com>
License: GNU GENERAL PUBLIC LICENSE
License-File: LICENSE
Keywords: analysis,data,fast,numba,numpy,performance,statistics
Classifier: Development Status :: 4 - Beta
Classifier: Intended Audience :: Developers
Classifier: License :: OSI Approved :: GNU General Public License v3 (GPLv3)
Classifier: Operating System :: OS Independent
Classifier: Programming Language :: Python :: 3.9
Classifier: Programming Language :: Python :: 3.10
Classifier: Programming Language :: Python :: 3.11
Classifier: Programming Language :: Python :: 3.12
Classifier: Programming Language :: Python :: 3.13
Requires-Python: >=3.9
Requires-Dist: numba
Requires-Dist: numpy
Provides-Extra: benchmark
Requires-Dist: tabulate; extra == 'benchmark'
Provides-Extra: dev
Requires-Dist: black; extra == 'dev'
Requires-Dist: pyyaml; extra == 'dev'
Provides-Extra: test
Requires-Dist: pytest-cov>=4.0.0; extra == 'test'
Requires-Dist: pytest>=7.0.0; extra == 'test'
